sqlatk/.DS_Store
sqlatk/__init__.py
sqlatk/database.py
sqlatk/model_schema.py
sqlatk-1.0.0.dist-info/WHEEL
sqlatk-1.0.0.dist-info/METADATA
sqlatk-1.0.0.dist-info/RECORD
