Metadata-Version: 2.1
Name: sqlatk
Version: 1.0.0
Summary: async database toolkit for fastapi
License: MIT
Author: wayfaring-stranger
Author-email: zw6p226m@duck.com
Requires-Python: >=3.9,<4.0
Classifier: License :: OSI Approved :: MIT License
Classifier: Programming Language :: Python :: 3
Classifier: Programming Language :: Python :: 3.9
Classifier: Programming Language :: Python :: 3.10
Classifier: Programming Language :: Python :: 3.11
Requires-Dist: asyncpg (==0.27.0)
Requires-Dist: databases (==0.7.0)
Requires-Dist: fastapi (==0.92.0)
Requires-Dist: loguru (==0.6.0)
Requires-Dist: pydantic (==1.10.5)
Requires-Dist: sqlalchemy (==2.0.3)
